README.md
setup.py
cmdbuild/__init__.py
cmdbuild/client.py
pycmdbuild.egg-info/PKG-INFO
pycmdbuild.egg-info/SOURCES.txt
pycmdbuild.egg-info/dependency_links.txt
pycmdbuild.egg-info/top_level.txt