Metadata-Version: 1.1
Name: pycmdbuild
Version: 0.1.2
Summary: Python library to access the REST interface of a CMDBuild server
Home-page: https://github.com/blazehu/pycmdbuild.git
Author: yhhu
Author-email: viease@foxmail.com
License: UNKNOWN
Platform: UNKNOWN
Requires: requests
